{"OutputFileHashSum":"42E142A6778D3897574B66D4876D69752721F743AB7815A0C0B0AEEAA56BD873","Converted":true,"OutputModifyDate":"2023-01-21T06:29:29.1245781Z","Metadatas":[{"CategoryName":"VuGen.Replay","Offset":516,"Length":23,"TypeId":1},{"CategoryName":"VuGen.Replay","Offset":3300,"Length":52,"TypeId":2},{"CategoryName":"VuGen.Replay","Offset":4297,"Length":150,"TypeId":3},{"CategoryName":"VuGen.Replay","Offset":4599,"Length":110,"TypeId":2},{"CategoryName":"VuGen.Replay","Offset":4709,"Length":67,"TypeId":4},{"CategoryName":"VuGen.Replay","Offset":4776,"Length":199,"TypeId":4},{"CategoryName":"VuGen.Replay","Offset":4998,"Length":21,"TypeId":1}],"MetadataTypes":[{"CategoryName":"VuGen.Replay","MetadataTypeName":"HP.LR.Vugen.Iteration","Id":1},{"CategoryName":"VuGen.Replay","MetadataTypeName":"HP.LR.Vugen.NotifyTransaction","Id":2},{"CategoryName":"VuGen.Replay","MetadataTypeName":"Utt.Debugger.Error","Id":3},{"CategoryName":"VuGen.Replay","MetadataTypeName":"HP.LR.Vugen.NotifyAny","Id":4}]}